thankyou/__init__.py
thankyou/tests.py
thankyou/thankyou.py
thankyou-0.0.3.dist-info/LICENSE
thankyou-0.0.3.dist-info/METADATA
thankyou-0.0.3.dist-info/WHEEL
thankyou-0.0.3.dist-info/entry_points.txt
thankyou-0.0.3.dist-info/RECORD
